nagoyaspray.py
nagoyaspray-1.1.0.dist-info/licenses/LICENSE.bak
nagoyaspray-1.1.0.dist-info/METADATA
nagoyaspray-1.1.0.dist-info/WHEEL
nagoyaspray-1.1.0.dist-info/entry_points.txt
nagoyaspray-1.1.0.dist-info/top_level.txt
nagoyaspray-1.1.0.dist-info/RECORD
