Metadata-Version: 2.4
Name: nagoyaspray
Version: 1.1.0
Summary: CTF-focused password spray wordlist generator for OSCP/PNPT/CPTS
Author-email: strikoder <strikoder@gmail.com>
Project-URL: Homepage, https://github.com/strikoder/NagoyaSpray
Project-URL: Repository, https://github.com/strikoder/NagoyaSpray
Project-URL: Issues, https://github.com/strikoder/NagoyaSpray/issues
Keywords: password-spray,wordlist-generator,oscp,pentesting,ctf,active-directory,pnpt,cpts
Classifier: Development Status :: 5 - Production/Stable
Classifier: Intended Audience :: Information Technology
Classifier: Topic :: Security
Classifier: Programming Language :: Python :: 3
Classifier: License :: OSI Approved :: GNU General Public License v3 (GPLv3)
Classifier: Operating System :: OS Independent
Requires-Python: >=3.6
License-File: LICENSE.bak
Dynamic: license-file
